{
  "date": "20190903",
  "generated_at": "2026-04-18T11:44:46.925927+09:00",
  "rankings": [
    {
      "rank": 1,
      "composite_rank": 1,
      "ticker": "032500",
      "name": "케이엠더블유",
      "score": 1.8403,
      "sector": "기타",
      "value_s": -1.2043,
      "quality_s": 0.7151,
      "momentum_s": 2.5825,
      "rev_z": 1.7028,
      "oca_z": 2.3062,
      "rev_accel_z": 1.3903,
      "gp_growth_z": 1.6517,
      "op_margin_z": 2.3062,
      "cfo_growth_z": 1.7028,
      "mom_6m_s": 2.4502,
      "mom_6m1m_s": 2.4221,
      "mom_12m_s": 2.5825,
      "mom_12m1m_s": 2.5588,
      "price": 73300
    },
    {
      "rank": 2,
      "composite_rank": 2,
      "ticker": "084680",
      "name": "이월드",
      "score": 1.5025,
      "sector": "기타",
      "value_s": -0.3242,
      "quality_s": -0.3254,
      "momentum_s": 1.3106,
      "rev_z": 2.3062,
      "oca_z": 1.0556,
      "rev_accel_z": 2.2865,
      "gp_growth_z": 1.8733,
      "op_margin_z": -0.8553,
      "cfo_growth_z": 2.3062,
      "mom_6m_s": 1.1031,
      "mom_6m1m_s": 0.9005,
      "mom_12m_s": 1.3106,
      "mom_12m1m_s": 1.3315,
      "price": 3345
    },
    {
      "rank": 3,
      "composite_rank": 3,
      "ticker": "101490",
      "name": "에스앤에스텍",
      "score": 0.9792,
      "sector": "기타",
      "value_s": -1.0838,
      "quality_s": -0.3591,
      "momentum_s": 1.6591,
      "rev_z": 1.0556,
      "oca_z": 0.9179,
      "rev_accel_z": 0.818,
      "gp_growth_z": 0.9125,
      "op_margin_z": 1.311,
      "cfo_growth_z": -0.4397,
      "mom_6m_s": 1.3998,
      "mom_6m1m_s": 1.4331,
      "mom_12m_s": 1.6591,
      "mom_12m1m_s": 1.7314,
      "price": 9800
    },
    {
      "rank": 4,
      "composite_rank": 4,
      "ticker": "060250",
      "name": "NHN KCP",
      "score": 0.9691,
      "sector": "기타",
      "value_s": -0.2687,
      "quality_s": 1.3546,
      "momentum_s": 1.4888,
      "rev_z": 0.5811,
      "oca_z": 1.311,
      "rev_accel_z": -1.0222,
      "gp_growth_z": 0.6561,
      "op_margin_z": 0.3006,
      "cfo_growth_z": 2.136,
      "mom_6m_s": 1.7163,
      "mom_6m1m_s": 1.6473,
      "mom_12m_s": 1.4888,
      "mom_12m1m_s": 1.3875,
      "price": 11699
    },
    {
      "rank": 5,
      "composite_rank": 5,
      "ticker": "181710",
      "name": "NHN",
      "score": 0.9588,
      "sector": "기타",
      "value_s": 0.9532,
      "quality_s": -0.2105,
      "momentum_s": 0.4732,
      "rev_z": 1.5449,
      "oca_z": 0.3006,
      "rev_accel_z": -1.1005,
      "gp_growth_z": 1.5449,
      "op_margin_z": 0.3905,
      "cfo_growth_z": 1.5449,
      "mom_6m_s": -0.0701,
      "mom_6m1m_s": 0.1564,
      "mom_12m_s": 0.4732,
      "mom_12m1m_s": 0.5597,
      "price": 60900
    },
    {
      "rank": 6,
      "composite_rank": 6,
      "ticker": "102710",
      "name": "이엔에프테크놀로지",
      "score": 0.7962,
      "sector": "기타",
      "value_s": 0.8764,
      "quality_s": 0.9997,
      "momentum_s": 0.6809,
      "rev_z": 0.5317,
      "oca_z": 0.9844,
      "rev_accel_z": 0.2476,
      "gp_growth_z": 0.5988,
      "op_margin_z": 0.0847,
      "cfo_growth_z": 0.0328,
      "mom_6m_s": 0.7701,
      "mom_6m1m_s": 0.8335,
      "mom_12m_s": 0.6809,
      "mom_12m1m_s": 0.6747,
      "price": 20550
    },
    {
      "rank": 7,
      "composite_rank": 7,
      "ticker": "012450",
      "name": "한화에어로스페이스",
      "score": 0.7909,
      "sector": "기타",
      "value_s": 0.4604,
      "quality_s": -0.7486,
      "momentum_s": 0.5407,
      "rev_z": 1.2169,
      "oca_z": 0.3452,
      "rev_accel_z": 1.1005,
      "gp_growth_z": 0.8433,
      "op_margin_z": 0.6845,
      "cfo_growth_z": 1.2169,
      "mom_6m_s": -0.0237,
      "mom_6m1m_s": -0.8203,
      "mom_12m_s": 0.5407,
      "mom_12m1m_s": 0.1591,
      "price": 41204
    },
    {
      "rank": 8,
      "composite_rank": 8,
      "ticker": "012610",
      "name": "경인양행",
      "score": 0.7611,
      "sector": "기타",
      "value_s": 0.0177,
      "quality_s": -0.7671,
      "momentum_s": 0.6721,
      "rev_z": 0.6845,
      "oca_z": 1.1326,
      "rev_accel_z": 0.5372,
      "gp_growth_z": 1.2501,
      "op_margin_z": 0.9179,
      "cfo_growth_z": 0.6845,
      "mom_6m_s": 0.5446,
      "mom_6m1m_s": 0.8982,
      "mom_12m_s": 0.6721,
      "mom_12m1m_s": 0.8844,
      "price": 7950
    },
    {
      "rank": 9,
      "composite_rank": 9,
      "ticker": "006400",
      "name": "삼성SDI",
      "score": 0.7607,
      "sector": "기타",
      "value_s": -0.4098,
      "quality_s": -0.6509,
      "momentum_s": 0.3743,
      "rev_z": 1.4182,
      "oca_z": 0.6319,
      "rev_accel_z": -1.1862,
      "gp_growth_z": 1.1532,
      "op_margin_z": 0.7958,
      "cfo_growth_z": 1.4182,
      "mom_6m_s": 0.1908,
      "mom_6m1m_s": 0.3956,
      "mom_12m_s": 0.3743,
      "mom_12m1m_s": 0.4649,
      "price": 241331
    },
    {
      "rank": 10,
      "composite_rank": 10,
      "ticker": "000990",
      "name": "DB하이텍",
      "score": 0.5865,
      "sector": "기타",
      "value_s": 0.6985,
      "quality_s": 0.7773,
      "momentum_s": -0.6705,
      "rev_z": 0.739,
      "oca_z": 1.5449,
      "rev_accel_z": 0.9498,
      "gp_growth_z": 0.7157,
      "op_margin_z": 1.2169,
      "cfo_growth_z": -0.6694,
      "mom_6m_s": -0.0456,
      "mom_6m1m_s": -0.2238,
      "mom_12m_s": -0.6705,
      "mom_12m1m_s": -0.6644,
      "price": 14850
    },
    {
      "rank": 11,
      "composite_rank": 11,
      "ticker": "036540",
      "name": "SFA반도체",
      "score": 0.5428,
      "sector": "기타",
      "value_s": 0.2742,
      "quality_s": -0.5087,
      "momentum_s": 0.2157,
      "rev_z": 0.9844,
      "oca_z": 0.2131,
      "rev_accel_z": 1.1862,
      "gp_growth_z": 0.7779,
      "op_margin_z": 0.2131,
      "cfo_growth_z": -0.3686,
      "mom_6m_s": 0.6826,
      "mom_6m1m_s": 0.6748,
      "mom_12m_s": 0.2157,
      "mom_12m1m_s": 0.2138,
      "price": 2555
    },
    {
      "rank": 12,
      "composite_rank": 12,
      "ticker": "049770",
      "name": "nan",
      "score": 0.4446,
      "sector": "기타",
      "value_s": 0.7168,
      "quality_s": 0.7757,
      "momentum_s": 0.9,
      "rev_z": 0.3905,
      "oca_z": -0.3452,
      "rev_accel_z": 0.3905,
      "gp_growth_z": -0.1417,
      "op_margin_z": -0.3452,
      "cfo_growth_z": 0.3905,
      "mom_6m_s": 0.7597,
      "mom_6m1m_s": 0.893,
      "mom_12m_s": 0.9,
      "mom_12m1m_s": 0.9434,
      "price": 216000
    },
    {
      "rank": 13,
      "composite_rank": 13,
      "ticker": "002150",
      "name": "도화엔지니어링",
      "score": 0.4377,
      "sector": "기타",
      "value_s": 0.0771,
      "quality_s": -0.1226,
      "momentum_s": -0.4552,
      "rev_z": 1.1326,
      "oca_z": 0.4836,
      "rev_accel_z": 1.2816,
      "gp_growth_z": 1.1326,
      "op_margin_z": 0.17,
      "cfo_growth_z": 0.7538,
      "mom_6m_s": -0.763,
      "mom_6m1m_s": -0.8982,
      "mom_12m_s": -0.4552,
      "mom_12m1m_s": -0.5215,
      "price": 10550
    },
    {
      "rank": 14,
      "composite_rank": 14,
      "ticker": "011280",
      "name": "태림포장",
      "score": 0.3727,
      "sector": "기타",
      "value_s": 0.2276,
      "quality_s": 0.2876,
      "momentum_s": 0.7766,
      "rev_z": -0.6845,
      "oca_z": 1.4182,
      "rev_accel_z": -0.7573,
      "gp_growth_z": 0.9864,
      "op_margin_z": 1.4182,
      "cfo_growth_z": 0.9416,
      "mom_6m_s": 0.2977,
      "mom_6m1m_s": 0.1115,
      "mom_12m_s": 0.7766,
      "mom_12m1m_s": 0.8811,
      "price": 6900
    },
    {
      "rank": 15,
      "composite_rank": 15,
      "ticker": "095660",
      "name": "네오위즈",
      "score": 0.3677,
      "sector": "기타",
      "value_s": 0.2539,
      "quality_s": 0.6905,
      "momentum_s": -0.463,
      "rev_z": 0.9179,
      "oca_z": 0.4365,
      "rev_accel_z": -0.882,
      "gp_growth_z": 0.4896,
      "op_margin_z": 0.2566,
      "cfo_growth_z": 1.4861,
      "mom_6m_s": -0.1849,
      "mom_6m1m_s": -0.5931,
      "mom_12m_s": -0.463,
      "mom_12m1m_s": -0.7258,
      "price": 16700
    },
    {
      "rank": 16,
      "composite_rank": 16,
      "ticker": "000270",
      "name": "기아",
      "score": 0.3616,
      "sector": "기타",
      "value_s": 1.4205,
      "quality_s": -0.549,
      "momentum_s": 0.7233,
      "rev_z": -0.5811,
      "oca_z": 0.5811,
      "rev_accel_z": -0.1116,
      "gp_growth_z": -0.2376,
      "op_margin_z": 0.5317,
      "cfo_growth_z": 0.4397,
      "mom_6m_s": 0.8335,
      "mom_6m1m_s": 0.824,
      "mom_12m_s": 0.7233,
      "mom_12m1m_s": 0.7883,
      "price": 43950
    },
    {
      "rank": 17,
      "composite_rank": 17,
      "ticker": "131370",
      "name": "알서포트",
      "score": 0.3406,
      "sector": "기타",
      "value_s": -0.9912,
      "quality_s": 1.0796,
      "momentum_s": 0.4144,
      "rev_z": 0.1273,
      "oca_z": 1.2169,
      "rev_accel_z": -0.3883,
      "gp_growth_z": 0.1273,
      "op_margin_z": 1.7028,
      "cfo_growth_z": 1.7226,
      "mom_6m_s": 0.5926,
      "mom_6m1m_s": 0.9987,
      "mom_12m_s": 0.4144,
      "mom_12m1m_s": 0.7775,
      "price": 3250
    },
    {
      "rank": 18,
      "composite_rank": 18,
      "ticker": "047810",
      "name": "한국항공우주",
      "score": 0.3383,
      "sector": "기타",
      "value_s": -0.7324,
      "quality_s": 0.2195,
      "momentum_s": -0.5421,
      "rev_z": 0.3006,
      "oca_z": 1.92,
      "rev_accel_z": -1.3903,
      "gp_growth_z": 2.2656,
      "op_margin_z": 1.92,
      "cfo_growth_z": 0.3006,
      "mom_6m_s": -0.4888,
      "mom_6m1m_s": -0.5344,
      "mom_12m_s": -0.5421,
      "mom_12m1m_s": -0.4843,
      "price": 39900
    },
    {
      "rank": 19,
      "composite_rank": 19,
      "ticker": "005880",
      "name": "대한해운",
      "score": 0.3207,
      "sector": "기타",
      "value_s": 2.0373,
      "quality_s": -0.0371,
      "momentum_s": -0.2645,
      "rev_z": 0.3452,
      "oca_z": -0.17,
      "rev_accel_z": -2.2865,
      "gp_growth_z": -0.4896,
      "op_margin_z": -0.4365,
      "cfo_growth_z": 0.6694,
      "mom_6m_s": -0.4602,
      "mom_6m1m_s": -0.2016,
      "mom_12m_s": -0.2645,
      "mom_12m1m_s": -0.1649,
      "price": 2264
    },
    {
      "rank": 20,
      "composite_rank": 20,
      "ticker": "003850",
      "name": "보령",
      "score": 0.2985,
      "sector": "기타",
      "value_s": -0.1795,
      "quality_s": 1.0889,
      "momentum_s": -0.3829,
      "rev_z": 0.0,
      "oca_z": 1.7028,
      "rev_accel_z": 0.2938,
      "gp_growth_z": 0.1417,
      "op_margin_z": 1.5449,
      "cfo_growth_z": 0.0,
      "mom_6m_s": -0.6593,
      "mom_6m1m_s": -0.5838,
      "mom_12m_s": -0.3829,
      "mom_12m1m_s": -0.4755,
      "price": 9286
    },
    {
      "rank": 21,
      "composite_rank": 21,
      "ticker": "086280",
      "name": "현대글로비스",
      "score": 0.2746,
      "sector": "기타",
      "value_s": 0.6533,
      "quality_s": 0.0407,
      "momentum_s": 0.5698,
      "rev_z": -0.0847,
      "oca_z": 0.1273,
      "rev_accel_z": 0.2019,
      "gp_growth_z": 0.386,
      "op_margin_z": -0.1273,
      "cfo_growth_z": -0.0847,
      "mom_6m_s": 0.2862,
      "mom_6m1m_s": 0.5344,
      "mom_12m_s": 0.5698,
      "mom_12m1m_s": 0.6173,
      "price": 77780
    },
    {
      "rank": 22,
      "composite_rank": 22,
      "ticker": "012330",
      "name": "현대모비스",
      "score": 0.2321,
      "sector": "기타",
      "value_s": 0.9285,
      "quality_s": -0.4706,
      "momentum_s": 0.4905,
      "rev_z": -0.2131,
      "oca_z": 0.0847,
      "rev_accel_z": -0.1566,
      "gp_growth_z": 0.2376,
      "op_margin_z": 0.1273,
      "cfo_growth_z": -0.2314,
      "mom_6m_s": 0.9652,
      "mom_6m1m_s": 1.0126,
      "mom_12m_s": 0.4905,
      "mom_12m1m_s": 0.5577,
      "price": 249000
    },
    {
      "rank": 23,
      "composite_rank": 23,
      "ticker": "007070",
      "name": "GS리테일",
      "score": 0.2137,
      "sector": "기타",
      "value_s": 0.7788,
      "quality_s": 0.5158,
      "momentum_s": 0.6515,
      "rev_z": -0.3006,
      "oca_z": 0.0423,
      "rev_accel_z": -0.0669,
      "gp_growth_z": 0.1894,
      "op_margin_z": -0.0423,
      "cfo_growth_z": 0.844,
      "mom_6m_s": 0.5191,
      "mom_6m1m_s": 0.4897,
      "mom_12m_s": 0.6515,
      "mom_12m1m_s": 0.5672,
      "price": 40100
    },
    {
      "rank": 24,
      "composite_rank": 24,
      "ticker": "005290",
      "name": "동진쎄미켐",
      "score": 0.2093,
      "sector": "기타",
      "value_s": -0.0723,
      "quality_s": 0.8922,
      "momentum_s": 0.4784,
      "rev_z": -0.3452,
      "oca_z": 0.7958,
      "rev_accel_z": -0.4368,
      "gp_growth_z": 0.3357,
      "op_margin_z": 0.5811,
      "cfo_growth_z": 0.1646,
      "mom_6m_s": 0.6205,
      "mom_6m1m_s": 0.6386,
      "mom_12m_s": 0.4784,
      "mom_12m1m_s": 0.5465,
      "price": 14600
    },
    {
      "rank": 25,
      "composite_rank": 25,
      "ticker": "007540",
      "name": "샘표",
      "score": 0.1248,
      "sector": "기타",
      "value_s": 1.0008,
      "quality_s": 0.4782,
      "momentum_s": -0.0244,
      "rev_z": -0.6319,
      "oca_z": 0.8553,
      "rev_accel_z": -0.0223,
      "gp_growth_z": -0.3357,
      "op_margin_z": 0.9844,
      "cfo_growth_z": -0.844,
      "mom_6m_s": -0.2039,
      "mom_6m1m_s": -0.3887,
      "mom_12m_s": -0.0244,
      "mom_12m1m_s": -0.1658,
      "price": 45400
    },
    {
      "rank": 26,
      "composite_rank": 26,
      "ticker": "064960",
      "name": "SNT모티브",
      "score": 0.0922,
      "sector": "기타",
      "value_s": 0.4896,
      "quality_s": -0.2052,
      "momentum_s": 1.5875,
      "rev_z": -0.8553,
      "oca_z": -0.5317,
      "rev_accel_z": 0.4864,
      "gp_growth_z": -0.9125,
      "op_margin_z": -0.3905,
      "cfo_growth_z": -0.8553,
      "mom_6m_s": 1.6579,
      "mom_6m1m_s": 1.7054,
      "mom_12m_s": 1.5875,
      "mom_12m1m_s": 1.5729,
      "price": 28540
    },
    {
      "rank": 27,
      "composite_rank": 27,
      "ticker": "031330",
      "name": "에스에이엠티",
      "score": 0.079,
      "sector": "기타",
      "value_s": 1.8582,
      "quality_s": 0.9422,
      "momentum_s": 0.1458,
      "rev_z": -0.3905,
      "oca_z": -0.3905,
      "rev_accel_z": 0.6992,
      "gp_growth_z": -0.5988,
      "op_margin_z": -0.2566,
      "cfo_growth_z": -0.3905,
      "mom_6m_s": 0.3197,
      "mom_6m1m_s": 0.5131,
      "mom_12m_s": 0.1458,
      "mom_12m1m_s": 0.2858,
      "price": 2085
    },
    {
      "rank": 28,
      "composite_rank": 28,
      "ticker": "023900",
      "name": "풍국주정",
      "score": -0.0207,
      "sector": "기타",
      "value_s": -0.3534,
      "quality_s": 0.3086,
      "momentum_s": 0.2432,
      "rev_z": 0.17,
      "oca_z": -0.4365,
      "rev_accel_z": -0.2938,
      "gp_growth_z": -0.5434,
      "op_margin_z": -0.5317,
      "cfo_growth_z": 0.2993,
      "mom_6m_s": -0.9533,
      "mom_6m1m_s": -0.6718,
      "mom_12m_s": 0.2432,
      "mom_12m1m_s": 0.4068,
      "price": 20000
    },
    {
      "rank": 29,
      "composite_rank": 29,
      "ticker": "035600",
      "name": "KG이니시스",
      "score": -0.027,
      "sector": "기타",
      "value_s": 1.0119,
      "quality_s": 1.4847,
      "momentum_s": -1.0479,
      "rev_z": 0.7958,
      "oca_z": -0.6845,
      "rev_accel_z": -0.2476,
      "gp_growth_z": -0.0943,
      "op_margin_z": -0.7958,
      "cfo_growth_z": -0.5895,
      "mom_6m_s": -0.8469,
      "mom_6m1m_s": -0.9828,
      "mom_12m_s": -1.0479,
      "mom_12m1m_s": -1.1372,
      "price": 15400
    },
    {
      "rank": 30,
      "composite_rank": 30,
      "ticker": "028670",
      "name": "팬오션",
      "score": -0.1527,
      "sector": "기타",
      "value_s": 0.4429,
      "quality_s": -0.695,
      "momentum_s": -0.4789,
      "rev_z": -0.1273,
      "oca_z": -0.1273,
      "rev_accel_z": -0.4864,
      "gp_growth_z": -0.4372,
      "op_margin_z": -0.3006,
      "cfo_growth_z": 0.5132,
      "mom_6m_s": 0.045,
      "mom_6m1m_s": -0.0,
      "mom_12m_s": -0.4789,
      "mom_12m1m_s": -0.4745,
      "price": 4885
    },
    {
      "rank": 31,
      "composite_rank": 31,
      "ticker": "104830",
      "name": "원익머트리얼즈",
      "score": -0.1764,
      "sector": "기타",
      "value_s": 0.4905,
      "quality_s": 0.5243,
      "momentum_s": -1.105,
      "rev_z": 0.0847,
      "oca_z": 0.17,
      "rev_accel_z": -0.5372,
      "gp_growth_z": 0.0847,
      "op_margin_z": 0.0847,
      "cfo_growth_z": -0.2993,
      "mom_6m_s": -1.0106,
      "mom_6m1m_s": -0.7612,
      "mom_12m_s": -1.105,
      "mom_12m1m_s": -0.8889,
      "price": 23850
    },
    {
      "rank": 32,
      "composite_rank": 32,
      "ticker": "035420",
      "name": "NAVER",
      "score": -0.271,
      "sector": "기타",
      "value_s": -1.3903,
      "quality_s": 0.3772,
      "momentum_s": -0.4206,
      "rev_z": 0.8553,
      "oca_z": -1.0556,
      "rev_accel_z": -0.2019,
      "gp_growth_z": 0.8553,
      "op_margin_z": -1.311,
      "cfo_growth_z": 0.8553,
      "mom_6m_s": -0.2035,
      "mom_6m1m_s": -0.2471,
      "mom_12m_s": -0.4206,
      "mom_12m1m_s": -0.4449,
      "price": 150500
    },
    {
      "rank": 33,
      "composite_rank": 33,
      "ticker": "008730",
      "name": "율촌화학",
      "score": -0.3014,
      "sector": "기타",
      "value_s": 0.1949,
      "quality_s": -0.7769,
      "momentum_s": 0.0949,
      "rev_z": -0.5317,
      "oca_z": -0.6319,
      "rev_accel_z": 0.3883,
      "gp_growth_z": -0.9864,
      "op_margin_z": -0.6845,
      "cfo_growth_z": 0.3686,
      "mom_6m_s": -0.0678,
      "mom_6m1m_s": 0.2035,
      "mom_12m_s": 0.0949,
      "mom_12m1m_s": 0.215,
      "price": 15850
    },
    {
      "rank": 34,
      "composite_rank": 34,
      "ticker": "011790",
      "name": "SKC",
      "score": -0.389,
      "sector": "기타",
      "value_s": 0.3251,
      "quality_s": -0.6484,
      "momentum_s": 0.0503,
      "rev_z": -1.0556,
      "oca_z": -0.2131,
      "rev_accel_z": -0.818,
      "gp_growth_z": -0.386,
      "op_margin_z": 0.0423,
      "cfo_growth_z": 0.5895,
      "mom_6m_s": 0.6,
      "mom_6m1m_s": 0.4101,
      "mom_12m_s": 0.0503,
      "mom_12m1m_s": 0.0,
      "price": 45500
    },
    {
      "rank": 35,
      "composite_rank": 35,
      "ticker": "021240",
      "name": "코웨이",
      "score": -0.4024,
      "sector": "기타",
      "value_s": -0.7802,
      "quality_s": 2.233,
      "momentum_s": -1.2482,
      "rev_z": -0.0423,
      "oca_z": 0.3905,
      "rev_accel_z": 0.0669,
      "gp_growth_z": 0.0943,
      "op_margin_z": -0.17,
      "cfo_growth_z": -0.1646,
      "mom_6m_s": -1.6413,
      "mom_6m1m_s": -1.3656,
      "mom_12m_s": -1.2482,
      "mom_12m1m_s": -1.1253,
      "price": 84700
    },
    {
      "rank": 36,
      "composite_rank": 36,
      "ticker": "053800",
      "name": "안랩",
      "score": -0.4095,
      "sector": "기타",
      "value_s": -0.8623,
      "quality_s": 1.3368,
      "momentum_s": -0.2635,
      "rev_z": -0.4836,
      "oca_z": -0.0847,
      "rev_accel_z": -0.3407,
      "gp_growth_z": -0.0471,
      "op_margin_z": -0.0847,
      "cfo_growth_z": 0.2314,
      "mom_6m_s": 0.0722,
      "mom_6m1m_s": -0.2471,
      "mom_12m_s": -0.2635,
      "mom_12m1m_s": -0.3583,
      "price": 62200
    },
    {
      "rank": 37,
      "composite_rank": 37,
      "ticker": "008350",
      "name": "남선알미늄",
      "score": -0.4518,
      "sector": "기타",
      "value_s": -0.27,
      "quality_s": 0.158,
      "momentum_s": 1.0971,
      "rev_z": -1.4182,
      "oca_z": -0.7958,
      "rev_accel_z": 0.4368,
      "gp_growth_z": -1.1532,
      "op_margin_z": -0.6319,
      "cfo_growth_z": -0.7538,
      "mom_6m_s": 0.559,
      "mom_6m1m_s": 0.2467,
      "mom_12m_s": 1.0971,
      "mom_12m1m_s": 0.9994,
      "price": 3595
    },
    {
      "rank": 38,
      "composite_rank": 38,
      "ticker": "039440",
      "name": "에스티아이",
      "score": -0.5704,
      "sector": "기타",
      "value_s": 0.7681,
      "quality_s": 1.4192,
      "momentum_s": -0.0237,
      "rev_z": -1.2169,
      "oca_z": -0.8553,
      "rev_accel_z": 0.1566,
      "gp_growth_z": -0.7779,
      "op_margin_z": -0.4836,
      "cfo_growth_z": 1.1704,
      "mom_6m_s": 0.4318,
      "mom_6m1m_s": 0.0446,
      "mom_12m_s": -0.0237,
      "mom_12m1m_s": -0.1417,
      "price": 16200
    },
    {
      "rank": 39,
      "composite_rank": 39,
      "ticker": "000660",
      "name": "SK하이닉스",
      "score": -0.8234,
      "sector": "기타",
      "value_s": 0.8141,
      "quality_s": 1.3938,
      "momentum_s": -0.7076,
      "rev_z": -0.9844,
      "oca_z": -1.4182,
      "rev_accel_z": -1.8974,
      "gp_growth_z": -1.2501,
      "op_margin_z": -1.7028,
      "cfo_growth_z": 0.0985,
      "mom_6m_s": -0.5431,
      "mom_6m1m_s": -0.3763,
      "mom_12m_s": -0.7076,
      "mom_12m1m_s": -0.6455,
      "price": 77000
    },
    {
      "rank": 40,
      "composite_rank": 40,
      "ticker": "064260",
      "name": "다날",
      "score": -0.8497,
      "sector": "기타",
      "value_s": 0.0029,
      "quality_s": -0.3059,
      "momentum_s": -1.4154,
      "rev_z": -0.739,
      "oca_z": -0.5811,
      "rev_accel_z": -1.6781,
      "gp_growth_z": -0.739,
      "op_margin_z": -0.739,
      "cfo_growth_z": -0.739,
      "mom_6m_s": -1.2929,
      "mom_6m1m_s": -1.4503,
      "mom_12m_s": -1.4154,
      "mom_12m1m_s": -1.7402,
      "price": 3380
    },
    {
      "rank": 41,
      "composite_rank": 41,
      "ticker": "093370",
      "name": "후성",
      "score": -0.8836,
      "sector": "기타",
      "value_s": -1.2891,
      "quality_s": -0.2309,
      "momentum_s": -0.4665,
      "rev_z": -0.7958,
      "oca_z": -0.9844,
      "rev_accel_z": -0.5895,
      "gp_growth_z": -1.0661,
      "op_margin_z": -0.9844,
      "cfo_growth_z": -1.3119,
      "mom_6m_s": -0.2374,
      "mom_6m1m_s": -0.1368,
      "mom_12m_s": -0.4665,
      "mom_12m1m_s": -0.3945,
      "price": 9229
    },
    {
      "rank": 42,
      "composite_rank": 42,
      "ticker": "084370",
      "name": "유진테크",
      "score": -0.9862,
      "sector": "기타",
      "value_s": 0.6315,
      "quality_s": 1.207,
      "momentum_s": -1.4154,
      "rev_z": -0.9179,
      "oca_z": -1.2169,
      "rev_accel_z": -1.5185,
      "gp_growth_z": -0.7157,
      "op_margin_z": -1.0556,
      "cfo_growth_z": 1.3119,
      "mom_6m_s": -1.1191,
      "mom_6m1m_s": -1.0478,
      "mom_12m_s": -1.4154,
      "mom_12m1m_s": -1.3556,
      "price": 12450
    }
  ],
  "metadata": {
    "universe_count": 436,
    "scored_count": 42,
    "ma120_passed": 99,
    "final_count": 42,
    "generator": "fast_generate_rankings_v2",
    "correlation_60d": {
      "032500_084680": 0.163,
      "032500_101490": 0.448,
      "032500_060250": 0.069,
      "032500_181710": 0.246,
      "032500_102710": 0.255,
      "012450_032500": 0.283,
      "012610_032500": 0.008,
      "006400_032500": 0.264,
      "000990_032500": 0.231,
      "032500_036540": 0.4,
      "032500_049770": 0.074,
      "002150_032500": -0.07,
      "011280_032500": 0.23,
      "032500_095660": 0.122,
      "000270_032500": 0.229,
      "032500_131370": 0.233,
      "032500_047810": 0.098,
      "005880_032500": 0.179,
      "003850_032500": 0.179,
      "032500_086280": 0.078,
      "012330_032500": 0.163,
      "007070_032500": 0.072,
      "005290_032500": -0.107,
      "007540_032500": 0.054,
      "032500_064960": 0.384,
      "031330_032500": 0.28,
      "023900_032500": 0.166,
      "032500_035600": 0.053,
      "028670_032500": 0.121,
      "084680_101490": 0.322,
      "060250_084680": 0.364,
      "084680_181710": 0.205,
      "084680_102710": 0.28,
      "012450_084680": -0.097,
      "012610_084680": 0.108,
      "006400_084680": -0.003,
      "000990_084680": 0.205,
      "036540_084680": 0.267,
      "049770_084680": 0.108,
      "002150_084680": 0.217,
      "011280_084680": 0.275,
      "084680_095660": 0.083,
      "000270_084680": 0.069,
      "084680_131370": 0.088,
      "047810_084680": -0.061,
      "005880_084680": -0.11,
      "003850_084680": 0.071,
      "084680_086280": 0.134,
      "012330_084680": -0.008,
      "007070_084680": -0.132,
      "005290_084680": 0.199,
      "007540_084680": -0.053,
      "064960_084680": 0.27,
      "031330_084680": 0.291,
      "023900_084680": 0.186,
      "035600_084680": 0.276,
      "028670_084680": -0.03,
      "060250_101490": 0.247,
      "101490_181710": 0.179,
      "101490_102710": 0.419,
      "012450_101490": 0.129,
      "012610_101490": -0.054,
      "006400_101490": 0.368,
      "000990_101490": 0.278,
      "036540_101490": 0.304,
      "049770_101490": -0.016,
      "002150_101490": 0.146,
      "011280_101490": 0.114,
      "095660_101490": 0.126,
      "000270_101490": -0.089,
      "101490_131370": 0.069,
      "047810_101490": 0.179,
      "005880_101490": 0.105,
      "003850_101490": -0.078,
      "086280_101490": 0.195,
      "012330_101490": 0.025,
      "007070_101490": -0.1,
      "005290_101490": 0.094,
      "007540_101490": 0.217,
      "064960_101490": 0.158,
      "031330_101490": 0.301,
      "023900_101490": 0.126,
      "035600_101490": 0.069,
      "028670_101490": 0.061,
      "060250_181710": 0.29,
      "060250_102710": 0.182,
      "012450_060250": 0.039,
      "012610_060250": -0.145,
      "006400_060250": 0.18,
      "000990_060250": 0.443,
      "036540_060250": 0.298,
      "049770_060250": 0.069,
      "002150_060250": 0.231,
      "011280_060250": 0.298,
      "060250_095660": 0.389,
      "000270_060250": 0.098,
      "060250_131370": 0.166,
      "047810_060250": 0.235,
      "005880_060250": -0.122,
      "003850_060250": 0.142,
      "060250_086280": 0.161,
      "012330_060250": -0.113,
      "007070_060250": -0.05,
      "005290_060250": 0.01,
      "007540_060250": -0.007,
      "060250_064960": 0.29,
      "031330_060250": 0.098,
      "023900_060250": 0.34,
      "035600_060250": 0.198,
      "028670_060250": 0.066,
      "102710_181710": 0.016,
      "012450_181710": 0.131,
      "012610_181710": -0.086,
      "006400_181710": 0.077,
      "000990_181710": 0.171,
      "036540_181710": 0.354,
      "049770_181710": 0.361,
      "002150_181710": 0.305,
      "011280_181710": 0.182,
      "095660_181710": 0.42,
      "000270_181710": 0.111,
      "131370_181710": 0.147,
      "047810_181710": 0.452,
      "005880_181710": 0.189,
      "003850_181710": 0.171,
      "086280_181710": 0.349,
      "012330_181710": 0.076,
      "007070_181710": 0.102,
      "005290_181710": -0.168,
      "007540_181710": -0.021,
      "064960_181710": 0.234,
      "031330_181710": -0.12,
      "023900_181710": 0.152,
      "035600_181710": 0.409,
      "028670_181710": 0.153,
      "012450_102710": 0.127,
      "012610_102710": 0.22,
      "006400_102710": 0.238,
      "000990_102710": 0.291,
      "036540_102710": 0.095,
      "049770_102710": -0.002,
      "002150_102710": 0.203,
      "011280_102710": 0.18,
      "095660_102710": 0.157,
      "000270_102710": 0.027,
      "102710_131370": -0.087,
      "047810_102710": 0.051,
      "005880_102710": 0.183,
      "003850_102710": 0.128,
      "086280_102710": -0.021,
      "012330_102710": -0.018,
      "007070_102710": -0.085,
      "005290_102710": 0.506,
      "007540_102710": -0.121,
      "064960_102710": 0.133,
      "031330_102710": 0.03,
      "023900_102710": -0.038,
      "035600_102710": -0.0,
      "028670_102710": 0.206,
      "012450_012610": -0.089,
      "006400_012450": 0.19,
      "000990_012450": 0.189,
      "012450_036540": 0.228,
      "012450_049770": 0.159,
      "002150_012450": 0.231,
      "011280_012450": 0.427,
      "012450_095660": 0.262,
      "000270_012450": 0.146,
      "012450_131370": 0.08,
      "012450_047810": 0.372,
      "005880_012450": 0.348,
      "003850_012450": 0.117,
      "012450_086280": 0.013,
      "012330_012450": -0.079,
      "007070_012450": 0.094,
      "005290_012450": -0.089,
      "007540_012450": 0.039,
      "012450_064960": 0.263,
      "012450_031330": 0.046,
      "012450_023900": 0.18,
      "012450_035600": 0.045,
      "012450_028670": 0.298,
      "006400_012610": 0.029,
      "000990_012610": 0.082,
      "012610_036540": -0.014,
      "012610_049770": -0.109,
      "002150_012610": -0.268,
      "011280_012610": -0.234,
      "012610_095660": -0.088,
      "000270_012610": -0.129,
      "012610_131370": -0.147,
      "012610_047810": -0.244,
      "005880_012610": -0.055,
      "003850_012610": -0.088,
      "012610_086280": -0.124,
      "012330_012610": -0.007,
      "007070_012610": -0.221,
      "005290_012610": 0.268,
      "007540_012610": -0.168,
      "012610_064960": 0.196,
      "012610_031330": -0.254,
      "012610_023900": -0.202,
      "012610_035600": -0.052,
      "012610_028670": -0.169,
      "000990_006400": 0.382,
      "006400_036540": 0.305,
      "006400_049770": 0.066,
      "002150_006400": 0.365,
      "006400_011280": 0.083,
      "006400_095660": 0.217,
      "000270_006400": 0.155,
      "006400_131370": 0.114,
      "006400_047810": 0.199,
      "005880_006400": 0.329,
      "003850_006400": 0.129,
      "006400_086280": 0.262,
      "006400_012330": 0.221,
      "006400_007070": 0.063,
      "005290_006400": 0.005,
      "006400_007540": -0.136,
      "006400_064960": 0.229,
      "006400_031330": 0.131,
      "006400_023900": 0.203,
      "006400_035600": 0.26,
      "006400_028670": 0.409,
      "000990_036540": 0.321,
      "000990_049770": 0.108,
      "000990_002150": 0.356,
      "000990_011280": 0.301,
      "000990_095660": 0.282,
      "000270_000990": 0.036,
      "000990_131370": 0.152,
      "000990_047810": 0.358,
      "000990_005880": 0.105,
      "000990_003850": 0.171,
      "000990_086280": 0.274,
      "000990_012330": 0.017,
      "000990_007070": 0.079,
      "000990_005290": -0.025,
      "000990_007540": -0.006,
      "000990_064960": 0.216,
      "000990_031330": 0.17,
      "000990_023900": 0.436,
      "000990_035600": 0.24,
      "000990_028670": 0.063,
      "036540_049770": 0.038,
      "002150_036540": 0.338,
      "011280_036540": 0.29,
      "036540_095660": 0.334,
      "000270_036540": 0.329,
      "036540_131370": 0.365,
      "036540_047810": 0.351,
      "005880_036540": 0.284,
      "003850_036540": 0.329,
      "036540_086280": 0.441,
      "012330_036540": 0.06,
      "007070_036540": -0.013,
      "005290_036540": -0.264,
      "007540_036540": -0.003,
      "036540_064960": 0.291,
      "031330_036540": 0.313,
      "023900_036540": 0.088,
      "035600_036540": 0.335,
      "028670_036540": 0.35,
      "002150_049770": 0.147,
      "011280_049770": -0.029,
      "049770_095660": 0.171,
      "000270_049770": -0.002,
      "049770_131370": -0.037,
      "047810_049770": 0.194,
      "005880_049770": 0.188,
      "003850_049770": -0.059,
      "049770_086280": 0.156,
      "012330_049770": -0.017,
      "007070_049770": 0.029,
      "005290_049770": -0.069,
      "007540_049770": -0.148,
      "049770_064960": 0.07,
      "031330_049770": 0.002,
      "023900_049770": 0.22,
      "035600_049770": 0.216,
      "028670_049770": 0.183,
      "002150_011280": 0.378,
      "002150_095660": 0.283,
      "000270_002150": 0.198,
      "002150_131370": 0.101,
      "002150_047810": 0.441,
      "002150_005880": 0.266,
      "002150_003850": 0.483,
      "002150_086280": 0.372,
      "002150_012330": 0.281,
      "002150_007070": 0.134,
      "002150_005290": 0.065,
      "002150_007540": -0.266,
      "002150_064960": 0.072,
      "002150_031330": 0.2,
      "002150_023900": 0.177,
      "002150_035600": 0.498,
      "002150_028670": 0.385,
      "011280_095660": 0.397,
      "000270_011280": 0.276,
      "011280_131370": 0.038,
      "011280_047810": 0.392,
      "005880_011280": 0.252,
      "003850_011280": 0.384,
      "011280_086280": 0.168,
      "011280_012330": 0.134,
      "007070_011280": 0.16,
      "005290_011280": 0.001,
      "007540_011280": -0.122,
      "011280_064960": 0.241,
      "011280_031330": 0.288,
      "011280_023900": 0.413,
      "011280_035600": 0.304,
      "011280_028670": 0.247,
      "000270_095660": 0.175,
      "095660_131370": 0.018,
      "047810_095660": 0.457,
      "005880_095660": 0.34,
      "003850_095660": 0.252,
      "086280_095660": 0.152,
      "012330_095660": 0.098,
      "007070_095660": 0.222,
      "005290_095660": -0.11,
      "007540_095660": -0.066,
      "064960_095660": 0.044,
      "031330_095660": 0.13,
      "023900_095660": 0.229,
      "035600_095660": 0.283,
      "028670_095660": 0.195,
      "000270_131370": 0.036,
      "000270_047810": 0.144,
      "000270_005880": 0.232,
      "000270_003850": 0.084,
      "000270_086280": 0.324,
      "000270_012330": 0.321,
      "000270_007070": 0.01,
      "000270_005290": -0.038,
      "000270_007540": 0.0,
      "000270_064960": 0.287,
      "000270_031330": 0.256,
      "000270_023900": 0.17,
      "000270_035600": 0.271,
      "000270_028670": 0.234,
      "047810_131370": 0.099,
      "005880_131370": 0.021,
      "003850_131370": 0.068,
      "086280_131370": 0.292,
      "012330_131370": 0.103,
      "007070_131370": -0.092,
      "005290_131370": -0.159,
      "007540_131370": 0.055,
      "064960_131370": -0.099,
      "031330_131370": 0.287,
      "023900_131370": 0.17,
      "035600_131370": 0.109,
      "028670_131370": 0.109,
      "005880_047810": 0.187,
      "003850_047810": 0.189,
      "047810_086280": 0.16,
      "012330_047810": 0.034,
      "007070_047810": 0.346,
      "005290_047810": -0.222,
      "007540_047810": -0.1,
      "047810_064960": 0.063,
      "031330_047810": 0.097,
      "023900_047810": 0.241,
      "035600_047810": 0.385,
      "028670_047810": 0.124,
      "003850_005880": 0.227,
      "005880_086280": 0.089,
      "005880_012330": 0.205,
      "005880_007070": 0.129,
      "005290_005880": 0.076,
      "005880_007540": -0.041,
      "005880_064960": 0.195,
      "005880_031330": 0.28,
      "005880_023900": 0.116,
      "005880_035600": 0.29,
      "005880_028670": 0.633,
      "003850_086280": 0.042,
      "003850_012330": 0.189,
      "003850_007070": 0.18,
      "003850_005290": -0.133,
      "003850_007540": -0.121,
      "003850_064960": 0.098,
      "003850_031330": 0.188,
      "003850_023900": -0.038,
      "003850_035600": 0.229,
      "003850_028670": 0.431,
      "012330_086280": 0.307,
      "007070_086280": -0.054,
      "005290_086280": -0.006,
      "007540_086280": -0.036,
      "064960_086280": 0.271,
      "031330_086280": 0.138,
      "023900_086280": 0.167,
      "035600_086280": 0.366,
      "028670_086280": 0.124,
      "007070_012330": 0.052,
      "005290_012330": 0.055,
      "007540_012330": -0.069,
      "012330_064960": 0.123,
      "012330_031330": 0.19,
      "012330_023900": -0.026,
      "012330_035600": 0.334,
      "012330_028670": 0.161,
      "005290_007070": -0.204,
      "007070_007540": 0.037,
      "007070_064960": 0.08,
      "007070_031330": -0.145,
      "007070_023900": 0.078,
      "007070_035600": 0.052,
      "007070_028670": 0.019,
      "005290_007540": -0.225,
      "005290_064960": 0.006,
      "005290_031330": -0.002,
      "005290_023900": -0.228,
      "005290_035600": -0.096,
      "005290_028670": -0.016,
      "007540_064960": -0.02,
      "007540_031330": -0.066,
      "007540_023900": -0.077,
      "007540_035600": -0.266,
      "007540_028670": -0.168,
      "031330_064960": -0.002,
      "023900_064960": 0.119,
      "035600_064960": 0.197,
      "028670_064960": 0.231,
      "023900_031330": 0.243,
      "031330_035600": 0.216,
      "028670_031330": 0.194,
      "023900_035600": 0.172,
      "023900_028670": -0.006,
      "028670_035600": 0.233
    },
    "ma120_failed": [
      "005930",
      "005380",
      "068270",
      "017670",
      "051900",
      "207940",
      "028260",
      "015760",
      "018260",
      "034730",
      "033780",
      "003550",
      "066570",
      "090430",
      "010130",
      "251270",
      "009540",
      "011170",
      "030200",
      "009150",
      "018880",
      "035250",
      "032640",
      "034220",
      "004020",
      "010140",
      "000720",
      "078930",
      "023530",
      "036460",
      "161390",
      "097950",
      "000210",
      "128940",
      "008770",
      "000120",
      "139480",
      "003670",
      "028050",
      "030000",
      "000100",
      "009830",
      "006360",
      "004170",
      "011070",
      "001040",
      "017800",
      "011780",
      "003490",
      "069620",
      "069960",
      "012510",
      "180640",
      "010620",
      "064350",
      "009240",
      "294870",
      "009420",
      "031430",
      "020560",
      "011210",
      "161890",
      "035760",
      "086900",
      "036490",
      "253450",
      "028300",
      "056190",
      "240810",
      "247540",
      "068760",
      "025980",
      "003000",
      "018250",
      "003520",
      "006650",
      "145720",
      "001680",
      "012630",
      "008060",
      "071840",
      "105630",
      "079550",
      "192820",
      "079160",
      "267270",
      "003230",
      "009450",
      "039130",
      "037560",
      "005690",
      "001820",
      "004430",
      "002990",
      "007460",
      "011690",
      "017960",
      "281820",
      "078520",
      "002100",
      "033920",
      "091810",
      "026890",
      "004710",
      "005070",
      "004980",
      "138490",
      "002020",
      "007660",
      "009270",
      "214420",
      "002450",
      "004310",
      "102280",
      "123690",
      "003350",
      "025620",
      "005420",
      "178920",
      "140410",
      "046890",
      "298380",
      "058470",
      "215600",
      "030190",
      "041960",
      "200130",
      "022100",
      "085660",
      "000250",
      "041510",
      "278280",
      "067160",
      "066970",
      "267980",
      "035900",
      "039840",
      "038540",
      "048260",
      "091700",
      "078130",
      "064760",
      "096530",
      "108320",
      "033290",
      "029960",
      "115450",
      "112040",
      "036420",
      "039200",
      "141080",
      "090460",
      "078160",
      "031390",
      "230360",
      "086520",
      "272290",
      "196170",
      "092040",
      "048410",
      "215200",
      "058820",
      "061970",
      "122870",
      "048530",
      "036800",
      "045390",
      "065660",
      "007390",
      "237880",
      "122990",
      "088800",
      "044340",
      "255440",
      "041830",
      "047310",
      "052020",
      "036930",
      "192440",
      "097520",
      "228760",
      "010170",
      "095610",
      "108230",
      "053580",
      "060150",
      "174900",
      "131970",
      "041140",
      "074600",
      "067990",
      "123860",
      "086390",
      "089980",
      "136480",
      "166090",
      "078150",
      "121800",
      "226950",
      "009520",
      "039560",
      "143160",
      "036030",
      "191420",
      "251970",
      "086820",
      "054780",
      "086980",
      "040910",
      "195990",
      "201490",
      "148150",
      "037460",
      "045970",
      "036180",
      "073560",
      "236200",
      "059090",
      "012700",
      "066430",
      "264450",
      "122640",
      "014470",
      "179290",
      "078890",
      "067900",
      "001540",
      "060240",
      "027050",
      "036810",
      "052420",
      "037950",
      "203650",
      "039830",
      "047820",
      "049180",
      "900100",
      "054210",
      "037070",
      "033340",
      "013990",
      "094940"
    ]
  }
}