{
  "date": "20201224",
  "generated_at": "2026-03-31T22:16:31.349206+09:00",
  "rankings": [
    {
      "rank": 1,
      "composite_rank": 1,
      "ticker": "017960",
      "name": "한국카본",
      "score": 0.8056,
      "sector": "금속",
      "value_s": 0.4302,
      "quality_s": 1.8399,
      "growth_s": 0.0,
      "momentum_s": 1.4057,
      "price": 13450
    },
    {
      "rank": 2,
      "composite_rank": 2,
      "ticker": "083930",
      "name": "아바코",
      "score": 0.7196,
      "sector": "기계",
      "value_s": 0.939,
      "quality_s": 1.6956,
      "growth_s": 0.0,
      "momentum_s": 0.7742,
      "price": 10250
    },
    {
      "rank": 3,
      "composite_rank": 3,
      "ticker": "131290",
      "name": "티에스이",
      "score": 0.6965,
      "sector": "의료기기",
      "value_s": -0.0793,
      "quality_s": 1.9041,
      "growth_s": 0.0,
      "momentum_s": 1.1617,
      "price": 54800
    },
    {
      "rank": 4,
      "composite_rank": 4,
      "ticker": "013580",
      "name": "계룡건설",
      "score": 0.635,
      "sector": "건설",
      "value_s": 2.5991,
      "quality_s": 0.9012,
      "growth_s": 0.0,
      "momentum_s": 0.0993,
      "price": 27050
    },
    {
      "rank": 5,
      "composite_rank": 5,
      "ticker": "001390",
      "name": "KG케미칼",
      "score": 0.6047,
      "sector": "화학",
      "value_s": 2.8041,
      "quality_s": 0.2459,
      "growth_s": 0.0,
      "momentum_s": 0.6129,
      "price": 4710
    },
    {
      "rank": 6,
      "composite_rank": 6,
      "ticker": "006650",
      "name": "대한유화",
      "score": 0.5471,
      "sector": "화학",
      "value_s": 0.7528,
      "quality_s": 0.4541,
      "growth_s": 0.0,
      "momentum_s": 1.6032,
      "price": 220000
    },
    {
      "rank": 7,
      "composite_rank": 7,
      "ticker": "130660",
      "name": "한전산업",
      "score": 0.5364,
      "sector": "서비스",
      "value_s": 0.4995,
      "quality_s": 1.4748,
      "growth_s": 0.0,
      "momentum_s": 0.4636,
      "price": 4700
    },
    {
      "rank": 8,
      "composite_rank": 8,
      "ticker": "002900",
      "name": "TYM",
      "score": 0.505,
      "sector": "기계",
      "value_s": 0.9547,
      "quality_s": 0.5213,
      "growth_s": 0.0,
      "momentum_s": 1.1574,
      "price": 5124
    },
    {
      "rank": 9,
      "composite_rank": 9,
      "ticker": "000270",
      "name": "기아",
      "score": 0.5005,
      "sector": "자동차",
      "value_s": 0.3723,
      "quality_s": 0.0434,
      "growth_s": 0.0,
      "momentum_s": 2.1688,
      "price": 61700
    },
    {
      "rank": 10,
      "composite_rank": 10,
      "ticker": "045100",
      "name": "한양이엔지",
      "score": 0.5002,
      "sector": "서비스",
      "value_s": 1.1117,
      "quality_s": 1.084,
      "growth_s": 0.0,
      "momentum_s": 0.3122,
      "price": 16500
    },
    {
      "rank": 11,
      "composite_rank": 11,
      "ticker": "139480",
      "name": "이마트",
      "score": 0.4976,
      "sector": "유통",
      "value_s": 1.3955,
      "quality_s": 0.3442,
      "growth_s": 0.0,
      "momentum_s": 1.0113,
      "price": 151000
    },
    {
      "rank": 12,
      "composite_rank": 12,
      "ticker": "006120",
      "name": "SK디스커버리",
      "score": 0.4405,
      "sector": "금융",
      "value_s": 1.7525,
      "quality_s": 0.4347,
      "growth_s": 0.0,
      "momentum_s": 0.3449,
      "price": 64800
    },
    {
      "rank": 13,
      "composite_rank": 13,
      "ticker": "053690",
      "name": "한미글로벌",
      "score": 0.4077,
      "sector": "서비스",
      "value_s": 0.9413,
      "quality_s": 1.3569,
      "growth_s": 0.0,
      "momentum_s": -0.3634,
      "price": 10200
    },
    {
      "rank": 14,
      "composite_rank": 14,
      "ticker": "011500",
      "name": "한농화성",
      "score": 0.4035,
      "sector": "화학",
      "value_s": 0.5151,
      "quality_s": 0.4711,
      "growth_s": 0.0,
      "momentum_s": 1.0421,
      "price": 8720
    },
    {
      "rank": 15,
      "composite_rank": 15,
      "ticker": "014680",
      "name": "한솔케미칼",
      "score": 0.3911,
      "sector": "화학",
      "value_s": -0.479,
      "quality_s": 1.8176,
      "growth_s": 0.0,
      "momentum_s": 0.0428,
      "price": 184000
    },
    {
      "rank": 16,
      "composite_rank": 16,
      "ticker": "120110",
      "name": "코오롱인더",
      "score": 0.3728,
      "sector": "화학",
      "value_s": 1.5931,
      "quality_s": 0.4221,
      "growth_s": 0.0,
      "momentum_s": 0.1416,
      "price": 40050
    },
    {
      "rank": 17,
      "composite_rank": 17,
      "ticker": "011200",
      "name": "HMM",
      "score": 0.3432,
      "sector": "물류",
      "value_s": -0.5113,
      "quality_s": -0.1197,
      "growth_s": 0.0,
      "momentum_s": 2.2492,
      "price": 12850
    },
    {
      "rank": 18,
      "composite_rank": 18,
      "ticker": "033780",
      "name": "KT&G",
      "score": 0.3396,
      "sector": "음식료",
      "value_s": 0.2264,
      "quality_s": 1.3199,
      "growth_s": 0.0,
      "momentum_s": -0.1217,
      "price": 88400
    },
    {
      "rank": 19,
      "composite_rank": 19,
      "ticker": "089010",
      "name": "켐트로닉스",
      "score": 0.3069,
      "sector": "화학",
      "value_s": -0.4237,
      "quality_s": 0.4048,
      "growth_s": 0.0,
      "momentum_s": 1.3463,
      "price": 27250
    },
    {
      "rank": 20,
      "composite_rank": 20,
      "ticker": "012200",
      "name": "계양전기",
      "score": 0.3002,
      "sector": "기계",
      "value_s": 0.9692,
      "quality_s": 0.5026,
      "growth_s": 0.0,
      "momentum_s": 0.1457,
      "price": 2530
    },
    {
      "rank": 21,
      "composite_rank": 21,
      "ticker": "005850",
      "name": "에스엘",
      "score": 0.2922,
      "sector": "자동차",
      "value_s": 0.7134,
      "quality_s": -0.4114,
      "growth_s": 0.0,
      "momentum_s": 1.4404,
      "price": 16300
    },
    {
      "rank": 22,
      "composite_rank": 22,
      "ticker": "023410",
      "name": "유진기업",
      "score": 0.2902,
      "sector": "비금속",
      "value_s": 1.5819,
      "quality_s": -0.4325,
      "growth_s": 0.0,
      "momentum_s": 0.8052,
      "price": 4810
    },
    {
      "rank": 23,
      "composite_rank": 23,
      "ticker": "105630",
      "name": "한세실업",
      "score": 0.2859,
      "sector": "섬유/의류",
      "value_s": 0.5021,
      "quality_s": 0.3381,
      "growth_s": 0.0,
      "momentum_s": 0.6302,
      "price": 18000
    },
    {
      "rank": 24,
      "composite_rank": 24,
      "ticker": "030000",
      "name": "제일기획",
      "score": 0.26,
      "sector": "서비스",
      "value_s": -0.0476,
      "quality_s": 1.3711,
      "growth_s": 0.0,
      "momentum_s": -0.378,
      "price": 21250
    },
    {
      "rank": 25,
      "composite_rank": 25,
      "ticker": "061970",
      "name": "LB세미콘",
      "score": 0.2509,
      "sector": "전기전자",
      "value_s": -0.1241,
      "quality_s": 0.7191,
      "growth_s": 0.0,
      "momentum_s": 0.4489,
      "price": 12550
    },
    {
      "rank": 26,
      "composite_rank": 26,
      "ticker": "054920",
      "name": "한컴위드",
      "score": 0.2131,
      "sector": "IT서비스",
      "value_s": -0.3675,
      "quality_s": -0.6153,
      "growth_s": 0.0,
      "momentum_s": 2.1105,
      "price": 6200
    },
    {
      "rank": 27,
      "composite_rank": 27,
      "ticker": "095610",
      "name": "테스",
      "score": 0.2066,
      "sector": "기계",
      "value_s": -0.3393,
      "quality_s": 1.0781,
      "growth_s": 0.0,
      "momentum_s": -0.0602,
      "price": 28950
    },
    {
      "rank": 28,
      "composite_rank": 28,
      "ticker": "009290",
      "name": "광동제약",
      "score": 0.1997,
      "sector": "바이오/제약",
      "value_s": 0.4103,
      "quality_s": 0.7847,
      "growth_s": 0.0,
      "momentum_s": -0.2903,
      "price": 10150
    },
    {
      "rank": 29,
      "composite_rank": 29,
      "ticker": "103140",
      "name": "풍산",
      "score": 0.1755,
      "sector": "금속",
      "value_s": 0.8653,
      "quality_s": -0.2979,
      "growth_s": 0.0,
      "momentum_s": 0.6007,
      "price": 27400
    },
    {
      "rank": 30,
      "composite_rank": 30,
      "ticker": "099320",
      "name": "쎄트렉아이",
      "score": 0.1225,
      "sector": "자동차",
      "value_s": -0.5744,
      "quality_s": 0.8873,
      "growth_s": 0.0,
      "momentum_s": -0.066,
      "price": 28900
    },
    {
      "rank": 31,
      "composite_rank": 31,
      "ticker": "100090",
      "name": "SK오션플랜트",
      "score": 0.1211,
      "sector": "금속",
      "value_s": -0.5258,
      "quality_s": -0.5998,
      "growth_s": 0.0,
      "momentum_s": 1.7496,
      "price": 19300
    },
    {
      "rank": 32,
      "composite_rank": 32,
      "ticker": "000390",
      "name": "삼화페인트",
      "score": 0.1042,
      "sector": "화학",
      "value_s": -0.5372,
      "quality_s": -0.2351,
      "growth_s": 0.0,
      "momentum_s": 1.2177,
      "price": 13550
    },
    {
      "rank": 33,
      "composite_rank": 33,
      "ticker": "090710",
      "name": "휴림로봇",
      "score": 0.0967,
      "sector": "기계",
      "value_s": -0.1887,
      "quality_s": -0.0692,
      "growth_s": 0.0,
      "momentum_s": 0.7114,
      "price": 4125
    },
    {
      "rank": 34,
      "composite_rank": 34,
      "ticker": "007210",
      "name": "nan",
      "score": 0.0688,
      "sector": "비금속",
      "value_s": 0.6065,
      "quality_s": -0.1229,
      "growth_s": 0.0,
      "momentum_s": 0.0428,
      "price": 2270
    },
    {
      "rank": 35,
      "composite_rank": 35,
      "ticker": "090430",
      "name": "아모레퍼시픽",
      "score": 0.061,
      "sector": "화학",
      "value_s": -1.3199,
      "quality_s": 0.8148,
      "growth_s": 0.0,
      "momentum_s": 0.2765,
      "price": 202500
    },
    {
      "rank": 36,
      "composite_rank": 36,
      "ticker": "003850",
      "name": "보령",
      "score": 0.0543,
      "sector": "바이오/제약",
      "value_s": -0.6007,
      "quality_s": 0.9973,
      "growth_s": 0.0,
      "momentum_s": -0.5244,
      "price": 14850
    },
    {
      "rank": 37,
      "composite_rank": 37,
      "ticker": "095340",
      "name": "ISC",
      "score": 0.0424,
      "sector": "유통",
      "value_s": -0.4214,
      "quality_s": 0.5474,
      "growth_s": 0.0,
      "momentum_s": -0.1561,
      "price": 25650
    },
    {
      "rank": 38,
      "composite_rank": 38,
      "ticker": "047040",
      "name": "대우건설",
      "score": 0.0329,
      "sector": "건설",
      "value_s": 1.1208,
      "quality_s": -0.3202,
      "growth_s": 0.0,
      "momentum_s": -0.2756,
      "price": 4645
    },
    {
      "rank": 39,
      "composite_rank": 39,
      "ticker": "001820",
      "name": "삼화콘덴서",
      "score": 0.0295,
      "sector": "전기전자",
      "value_s": -0.8622,
      "quality_s": 1.1965,
      "growth_s": 0.0,
      "momentum_s": -0.7015,
      "price": 61600
    },
    {
      "rank": 40,
      "composite_rank": 40,
      "ticker": "178920",
      "name": "PI첨단소재",
      "score": 0.0197,
      "sector": "화학",
      "value_s": -1.0097,
      "quality_s": 1.0892,
      "growth_s": 0.0,
      "momentum_s": -0.5058,
      "price": 36500
    },
    {
      "rank": 41,
      "composite_rank": 41,
      "ticker": "141000",
      "name": "비아트론",
      "score": 0.0193,
      "sector": "기계",
      "value_s": 0.2584,
      "quality_s": 0.2236,
      "growth_s": 0.0,
      "momentum_s": -0.3768,
      "price": 10550
    },
    {
      "rank": 42,
      "composite_rank": 42,
      "ticker": "069960",
      "name": "현대백화점",
      "score": 0.0162,
      "sector": "유통",
      "value_s": 0.5798,
      "quality_s": -0.3609,
      "growth_s": 0.0,
      "momentum_s": 0.0974,
      "price": 70500
    },
    {
      "rank": 43,
      "composite_rank": 43,
      "ticker": "000100",
      "name": "유한양행",
      "score": 0.016,
      "sector": "바이오/제약",
      "value_s": -0.9791,
      "quality_s": 0.4204,
      "growth_s": 0.0,
      "momentum_s": 0.2888,
      "price": 61625
    },
    {
      "rank": 44,
      "composite_rank": 44,
      "ticker": "214390",
      "name": "경보제약",
      "score": 0.0135,
      "sector": "바이오/제약",
      "value_s": -0.8493,
      "quality_s": 0.2831,
      "growth_s": 0.0,
      "momentum_s": 0.3507,
      "price": 12365
    },
    {
      "rank": 45,
      "composite_rank": 45,
      "ticker": "200470",
      "name": "에이팩트",
      "score": 0.013,
      "sector": "전기전자",
      "value_s": -0.1255,
      "quality_s": 0.4296,
      "growth_s": 0.0,
      "momentum_s": -0.378,
      "price": 4714
    },
    {
      "rank": 46,
      "composite_rank": 46,
      "ticker": "078930",
      "name": "GS",
      "score": 0.0093,
      "sector": "금융",
      "value_s": 1.9092,
      "quality_s": -0.088,
      "growth_s": 0.0,
      "momentum_s": -1.2752,
      "price": 37500
    },
    {
      "rank": 47,
      "composite_rank": 47,
      "ticker": "054210",
      "name": "이랜텍",
      "score": -0.0056,
      "sector": "전기전자",
      "value_s": -0.2602,
      "quality_s": -0.4679,
      "growth_s": 0.0,
      "momentum_s": 0.7518,
      "price": 8380
    },
    {
      "rank": 48,
      "composite_rank": 48,
      "ticker": "082740",
      "name": "한화엔진",
      "score": -0.0236,
      "sector": "기계",
      "value_s": 0.0892,
      "quality_s": -0.6024,
      "growth_s": 0.0,
      "momentum_s": 0.5683,
      "price": 6315
    },
    {
      "rank": 49,
      "composite_rank": 49,
      "ticker": "092070",
      "name": "디엔에프",
      "score": -0.027,
      "sector": "화학",
      "value_s": -0.0023,
      "quality_s": 0.902,
      "growth_s": 0.0,
      "momentum_s": -1.2607,
      "price": 18600
    },
    {
      "rank": 50,
      "composite_rank": 50,
      "ticker": "084370",
      "name": "유진테크",
      "score": -0.0655,
      "sector": "기계",
      "value_s": -1.0573,
      "quality_s": 0.9658,
      "growth_s": 0.0,
      "momentum_s": -0.7417,
      "price": 31950
    },
    {
      "rank": 51,
      "composite_rank": 51,
      "ticker": "003550",
      "name": "LG",
      "score": -0.0878,
      "sector": "금융",
      "value_s": 0.4329,
      "quality_s": 0.0921,
      "growth_s": 0.0,
      "momentum_s": -0.879,
      "price": 80296
    },
    {
      "rank": 52,
      "composite_rank": 52,
      "ticker": "091700",
      "name": "파트론",
      "score": -0.1125,
      "sector": "전기전자",
      "value_s": -0.2161,
      "quality_s": -0.1239,
      "growth_s": 0.0,
      "momentum_s": -0.2454,
      "price": 10450
    },
    {
      "rank": 53,
      "composite_rank": 53,
      "ticker": "009470",
      "name": "삼화전기",
      "score": -0.1306,
      "sector": "전기전자",
      "value_s": -0.288,
      "quality_s": 0.2115,
      "growth_s": 0.0,
      "momentum_s": -0.7015,
      "price": 20000
    },
    {
      "rank": 54,
      "composite_rank": 54,
      "ticker": "011790",
      "name": "SKC",
      "score": -0.1422,
      "sector": "화학",
      "value_s": -0.4778,
      "quality_s": -0.4382,
      "growth_s": 0.0,
      "momentum_s": 0.1951,
      "price": 91600
    },
    {
      "rank": 55,
      "composite_rank": 55,
      "ticker": "145720",
      "name": "덴티움",
      "score": -0.1498,
      "sector": "의료기기",
      "value_s": -0.3993,
      "quality_s": 0.4654,
      "growth_s": 0.0,
      "momentum_s": -1.0313,
      "price": 40150
    },
    {
      "rank": 56,
      "composite_rank": 56,
      "ticker": "131970",
      "name": "두산테스나",
      "score": -0.1637,
      "sector": "서비스",
      "value_s": -1.0441,
      "quality_s": 0.4232,
      "growth_s": 0.0,
      "momentum_s": -0.5647,
      "price": 49900
    },
    {
      "rank": 57,
      "composite_rank": 57,
      "ticker": "004310",
      "name": "현대약품",
      "score": -0.1648,
      "sector": "바이오/제약",
      "value_s": -1.0949,
      "quality_s": 0.4678,
      "growth_s": 0.0,
      "momentum_s": -0.5876,
      "price": 7440
    },
    {
      "rank": 58,
      "composite_rank": 58,
      "ticker": "018260",
      "name": "삼성에스디에스",
      "score": -0.1955,
      "sector": "IT서비스",
      "value_s": -0.3728,
      "quality_s": 0.4066,
      "growth_s": 0.0,
      "momentum_s": -1.2059,
      "price": 179500
    },
    {
      "rank": 59,
      "composite_rank": 59,
      "ticker": "009540",
      "name": "HD한국조선해양",
      "score": -0.1981,
      "sector": "금융",
      "value_s": 0.4757,
      "quality_s": -0.8482,
      "growth_s": 0.0,
      "momentum_s": -0.2871,
      "price": 108000
    },
    {
      "rank": 60,
      "composite_rank": 60,
      "ticker": "000120",
      "name": "CJ대한통운",
      "score": -0.2063,
      "sector": "물류",
      "value_s": 0.3703,
      "quality_s": -0.3317,
      "growth_s": 0.0,
      "momentum_s": -0.8945,
      "price": 163500
    },
    {
      "rank": 61,
      "composite_rank": 61,
      "ticker": "013030",
      "name": "하이록코리아",
      "score": -0.2386,
      "sector": "금속",
      "value_s": 0.3971,
      "quality_s": -0.2595,
      "growth_s": 0.0,
      "momentum_s": -1.1667,
      "price": 14300
    },
    {
      "rank": 62,
      "composite_rank": 62,
      "ticker": "161890",
      "name": "한국콜마",
      "score": -0.2491,
      "sector": "화학",
      "value_s": -0.1943,
      "quality_s": -0.1814,
      "growth_s": 0.0,
      "momentum_s": -0.873,
      "price": 47750
    },
    {
      "rank": 63,
      "composite_rank": 63,
      "ticker": "039030",
      "name": "이오테크닉스",
      "score": -0.258,
      "sector": "기계",
      "value_s": -1.2481,
      "quality_s": 0.4459,
      "growth_s": 0.0,
      "momentum_s": -0.9113,
      "price": 110600
    },
    {
      "rank": 64,
      "composite_rank": 64,
      "ticker": "042660",
      "name": "한화오션",
      "score": -0.2762,
      "sector": "자동차",
      "value_s": 0.6171,
      "quality_s": -0.9505,
      "growth_s": 0.0,
      "momentum_s": -0.6557,
      "price": 23676
    },
    {
      "rank": 65,
      "composite_rank": 65,
      "ticker": "075580",
      "name": "세진중공업",
      "score": -0.3482,
      "sector": "자동차",
      "value_s": -1.1396,
      "quality_s": -0.7898,
      "growth_s": 0.0,
      "momentum_s": 0.1008,
      "price": 6670
    },
    {
      "rank": 66,
      "composite_rank": 66,
      "ticker": "039440",
      "name": "에스티아이",
      "score": -0.3623,
      "sector": "기계",
      "value_s": 0.0869,
      "quality_s": -0.309,
      "growth_s": 0.0,
      "momentum_s": -1.4905,
      "price": 17300
    },
    {
      "rank": 67,
      "composite_rank": 67,
      "ticker": "005070",
      "name": "코스모신소재",
      "score": -0.3787,
      "sector": "화학",
      "value_s": -1.0673,
      "quality_s": -0.7869,
      "growth_s": 0.0,
      "momentum_s": -0.1096,
      "price": 18472
    },
    {
      "rank": 68,
      "composite_rank": 68,
      "ticker": "042000",
      "name": "카페24",
      "score": -0.4069,
      "sector": "IT서비스",
      "value_s": -1.2454,
      "quality_s": 0.2163,
      "growth_s": 0.0,
      "momentum_s": -1.371,
      "price": 31182
    }
  ],
  "metadata": {
    "universe_count": 1031,
    "scored_count": 68,
    "generator": "fast_generate_rankings"
  }
}